pycrfsuite/__init__.py
pycrfsuite/_dumpparser.py
pycrfsuite/_logparser.py
pycrfsuite/_pycrfsuite.cp36-win_amd64.pyd
python_crfsuite-0.9.10.dist-info/LICENSE.txt
python_crfsuite-0.9.10.dist-info/METADATA
python_crfsuite-0.9.10.dist-info/WHEEL
python_crfsuite-0.9.10.dist-info/top_level.txt
python_crfsuite-0.9.10.dist-info/RECORD
